django_vatno_validator-0.1.1.dist-info/DESCRIPTION.rst
django_vatno_validator-0.1.1.dist-info/METADATA
django_vatno_validator-0.1.1.dist-info/metadata.json
django_vatno_validator-0.1.1.dist-info/RECORD
django_vatno_validator-0.1.1.dist-info/top_level.txt
django_vatno_validator-0.1.1.dist-info/WHEEL
vatno_validator/__init__.py
vatno_validator/models.py
vatno_validator/validators.py
