Metadata-Version: 2.0
Name: django-vatno-validator
Version: 0.1.1
Summary: A Django validator that validates European VAT numbers
Home-page: https://github.com/productgang/django-vatno-validator
Author: Lukas Klein
Author-email: lukas@productgang.com
License: BSD
Keywords: django-vatno-validator
Platform: UNKNOWN
Classifier: Development Status :: 3 - Alpha
Classifier: Framework :: Django
Classifier: Framework :: Django :: 1.7
Classifier: Framework :: Django :: 1.8
Classifier: Intended Audience :: Developers
Classifier: License :: OSI Approved :: BSD License
Classifier: Natural Language :: English
Classifier: Programming Language :: Python :: 2
Classifier: Programming Language :: Python :: 2.7
Classifier: Programming Language :: Python :: 3
Classifier: Programming Language :: Python :: 3.3
Classifier: Programming Language :: Python :: 3.4
Classifier: Programming Language :: Python :: 3.5
